Workbook

Sheet Budget vs actual
A1: FY2024 budget versus actual
A2: Budget column is a simulation (see 'Budget basis'). Actual column is as filed. Variance is actual less budget; the favourable / unfavourable flag flips sign for expense lines.
A4: Line | B4: Budget (simulated) | C4: Actual (filed) | D4: Variance | E4: Variance % | F4: F / U | G4: Commentary
A5: Revenue
A6: Contributions and grants | B6: ='Source data'!F10*(1+'Budget basis'!$C$15)*('Source data'!F6/'Source data'!F10) | C6: ='Source data'!G6 | D6: =C6-B6 | E6: =IF(B6=0,"n/a",D6/ABS(B6)) | F6: =IF(D6>0,"Favourable","Unfavourable") | G6: Budget holds the FY2023 revenue mix and applies the 12% growth plan.
A7: Program service revenue | B7: ='Source data'!F10*(1+'Budget basis'!$C$15)*('Source data'!F7/'Source data'!F10) | C7: ='Source data'!G7 | D7: =C7-B7 | E7: =IF(B7=0,"n/a",D7/ABS(B7)) | F7: =IF(D7>0,"Favourable","Unfavourable")
A8: Investment and other income | B8: ='Source data'!F10*(1+'Budget basis'!$C$15)-B6-B7 | C8: ='Source data'!G8+'Source data'!G9 | D8: =C8-B8 | E8: =IF(B8=0,"n/a",D8/ABS(B8)) | F8: =IF(D8>0,"Favourable","Unfavourable") | G8: Actual combines investment income with the fundraising-event netting line so the two columns are measured on the same basis.
A9: Total revenue | B9: =SUM(B6:B8) | C9: ='Source data'!G10 | D9: =C9-B9 | E9: =IF(B9=0,"n/a",D9/ABS(B9)) | F9: =IF(D9>0,"Favourable","Unfavourable")
A11: Expenses
A12: Program services | B12: ='Source data'!F11*(1+'Budget basis'!$C$16)*'Source data'!F20 | C12: ='Source data'!G25 | D12: =C12-B12 | E12: =IF(B12=0,"n/a",D12/ABS(B12)) | F12: =IF(D12<0,"Favourable","Unfavourable") | G12: Budget applies the FY2023 functional split to the grown expense base.
A13: Management and general | B13: ='Source data'!F11*(1+'Budget basis'!$C$16)*'Source data'!F21 | C13: ='Source data'!G26 | D13: =C13-B13 | E13: =IF(B13=0,"n/a",D13/ABS(B13)) | F13: =IF(D13<0,"Favourable","Unfavourable")
A14: Fundraising | B14: ='Source data'!F11*(1+'Budget basis'!$C$16)*'Source data'!F22 | C14: ='Source data'!G27 | D14: =C14-B14 | E14: =IF(B14=0,"n/a",D14/ABS(B14)) | F14: =IF(D14<0,"Favourable","Unfavourable")
A15: Total expenses | B15: =SUM(B12:B14) | C15: ='Source data'!G11 | D15: =C15-B15 | E15: =IF(B15=0,"n/a",D15/ABS(B15)) | F15: =IF(D15<0,"Favourable","Unfavourable")
A17: Natural classification (memo)
A18: Personnel | B18: ='Source data'!F11*(1+'Budget basis'!$C$16)*('Source data'!F12+'Source data'!F13+'Source data'!F14+('Source data'!F12+'Source data'!F13)*0.1)/'Source data'!F11 | C18: ='Source data'!G12+'Source data'!G13+'Source data'!G14+('Source data'!G12+'Source data'!G13)*0.1 | D18: =C18-B18 | E18: =IF(B18=0,"n/a",D18/ABS(B18)) | F18: =IF(D18<0,"Favourable","Unfavourable") | G18: Budget holds the FY2023 personnel share of expenses constant.
A19: Non-personnel | B19: =B15-B18 | C19: =C15-C18 | D19: =C19-B19 | E19: =IF(B19=0,"n/a",D19/ABS(B19)) | F19: =IF(D19<0,"Favourable","Unfavourable")
A21: Result
A22: Operating surplus / (deficit) | B22: =B9-B15 | C22: =C9-C15 | D22: =C22-B22 | E22: =IF(B22=0,"n/a",D22/ABS(B22)) | F22: =IF(D22>0,"Favourable","Unfavourable")
A23: Operating margin | B23: =B22/B9 | C23: =C22/C9 | D23: =C23-B23 | E23: =IF(B23=0,"n/a",D23/ABS(B23)) | F23: =IF(D23>0,"Favourable","Unfavourable")
A24: Program expense ratio | B24: =B12/B15 | C24: =C12/C15 | D24: =C24-B24 | E24: =IF(B24=0,"n/a",D24/ABS(B24)) | F24: =IF(D24>0,"Favourable","Unfavourable")
A26: Volume and unit cost
A27: Participants served | B27: ='Source data'!F38*(1+'Budget basis'!$C$17) | C27: ='Source data'!G38 | D27: =C27-B27 | E27: =IF(B27=0,"n/a",D27/ABS(B27)) | F27: =IF(D27>0,"Favourable","Unfavourable")
A28: Successful outcomes | B28: =B27*('Source data'!F39/'Source data'!F38) | C28: ='Source data'!G39 | D28: =C28-B28 | E28: =IF(B28=0,"n/a",D28/ABS(B28)) | F28: =IF(D28>0,"Favourable","Unfavourable") | G28: Budget holds the FY2023 outcome rate constant on the planned participant count.
A29: Cost per participant | B29: =B12/B27 | C29: =C12/C27 | D29: =C29-B29 | E29: =IF(B29=0,"n/a",D29/ABS(B29)) | F29: =IF(D29<0,"Favourable","Unfavourable")
A30: Cost per successful outcome | B30: =B12/B28 | C30: =C12/C28 | D30: =C30-B30 | E30: =IF(B30=0,"n/a",D30/ABS(B30)) | F30: =IF(D30<0,"Favourable","Unfavourable")

Sheet Source data
A1: Source data
A2: Upwardly Global, EIN 94-3346127. Public Form 990 figures and the modelled splits this workbook depends on. Restated here so the file stands alone.
A4: Line | B4: FY2019 | C4: FY2020 | D4: FY2021 | E4: FY2022 | F4: FY2023 | G4: FY2024 | H4: Tier | I4: Note
A5: Form 990 as filed
A6: Contributions and grants | B6: 6528091 | C6: 6738370 | D6: 11624463 | E6: 18348946 | F6: 20709887 | G6: 26008174 | H6: PUBLIC
A7: Program service revenue | B7: 353671 | C7: 304509 | D7: 383141 | E7: 1064285 | F7: 1066130 | G7: 1143216 | H7: PUBLIC
A8: Investment and other income | B8: 3602 | C8: 21624 | D8: 237 | E8: 14416 | F8: 672813 | G8: 1429021 | H8: PUBLIC
A9: Less: fundraising event costs and asset-sale losses | B9: -135303 | C9: -48199 | D9: -34318 | E9: -121695 | F9: -57789 | G9: 0 | H9: DERIVED
A10: Total revenue | B10: 6750061 | C10: 7016304 | D10: 11973523 | E10: 19305952 | F10: 22391041 | G10: 28580411 | H10: PUBLIC
A11: Total functional expenses | B11: 5531091 | C11: 5670504 | D11: 6893690 | E11: 9316393 | F11: 13659379 | G11: 18275646 | H11: PUBLIC
A12: Officer compensation | B12: 336307 | C12: 348404 | D12: 537859 | E12: 642262 | F12: 502983 | G12: 1026038 | H12: PUBLIC
A13: Other salaries and wages | B13: 3257098 | C13: 3406913 | D13: 3755210 | E13: 5321071 | F13: 7253251 | G13: 9234306 | H13: PUBLIC
A14: Payroll taxes | B14: 283482 | C14: 290730 | D14: 339149 | E14: 454590 | F14: 606465 | G14: 800307 | H14: PUBLIC
A15: Total assets | B15: 4915534 | C15: 7157462 | D15: 12593796 | E15: 23406064 | F15: 31782416 | G15: 42583791 | H15: PUBLIC
A16: Total liabilities | B16: 461151 | C16: 1357279 | D16: 1713780 | E16: 2536489 | F16: 2181179 | G16: 2676737 | H16: PUBLIC
A17: Net assets | B17: =B15-B16 | C17: =C15-C16 | D17: =D15-D16 | E17: =E15-E16 | F17: =F15-F16 | G17: =G15-G16 | H17: DERIVED
A19: Modelled functional expense split
A20: Program services share | B20: 0.762 | C20: 0.768 | D20: 0.774 | E20: 0.78 | F20: 0.783 | G20: 0.785 | H20: SYNTHETIC
A21: Management and general share | B21: 0.14 | C21: 0.137 | D21: 0.134 | E21: 0.129 | F21: 0.124 | G21: 0.12 | H21: SYNTHETIC
A22: Fundraising share | B22: 0.098 | C22: 0.095 | D22: 0.092 | E22: 0.091 | F22: 0.093 | G22: 0.095 | H22: SYNTHETIC
A24: Derived expense lines
A25: Program services | B25: =B11*B20 | C25: =C11*C20 | D25: =D11*D20 | E25: =E11*E20 | F25: =F11*F20 | G25: =G11*G20
A26: Management and general | B26: =B11*B21 | C26: =C11*C21 | D26: =D11*D21 | E26: =E11*E21 | F26: =F11*F21 | G26: =G11*G21
A27: Fundraising | B27: =B11*B22 | C27: =C11*C22 | D27: =D11*D22 | E27: =E11*E22 | F27: =F11*F22 | G27: =G11*G22
A29: Interpolation anchors (published observations)
A30: 2022 participants | B30: 7041 | H30: PUBLIC
A31: 2025 participants | B31: 13350 | H31: PUBLIC
A32: Participant growth per year | B32: =(B31/B30)^(1/3)-1 | H32: DERIVED
A33: 2022 placements | B33: 1116 | H33: PUBLIC
A34: 2025 placements | B34: 1730 | H34: PUBLIC
A35: Placement growth per year | B35: =(B34/B33)^(1/3)-1 | H35: DERIVED
A37: Program volume
A38: Participants served | B38: =$B$30*(1+$B$32)^(2019-2022) | C38: =$B$30*(1+$B$32)^(2020-2022) | D38: =$B$30*(1+$B$32)^(2021-2022) | E38: =$B$30*(1+$B$32)^(2022-2022) | F38: =$B$30*(1+$B$32)^(2023-2022) | G38: =$B$30*(1+$B$32)^(2024-2022) | H38: DERIVED
A39: Successful outcomes | B39: =$B$33*(1+$B$35)^(2019-2022) | C39: =$B$33*(1+$B$35)^(2020-2022) | D39: =$B$33*(1+$B$35)^(2021-2022) | E39: =$B$33*(1+$B$35)^(2022-2022) | F39: =$B$33*(1+$B$35)^(2023-2022) | G39: =$B$33*(1+$B$35)^(2024-2022) | H39: DERIVED
A41: Participant and placement counts are published for 2022 and 2025 only. Other years are interpolated at constant growth between those two observations, which fixes the series with no free parameters. The back-cast to FY2019 through FY2021 is the weakest link and should be read as illustrative.

Sheet Budget basis
A1: Budget basis - reconstructed, not filed
A2: There is no public FY2024 budget for this organization. This sheet builds one, states exactly how, and labels it a simulation everywhere it appears.
B4: SIMULATED BUDGET. Every budget figure in this workbook is constructed by the author. It is not the organization's approved budget and does not represent its plans. Only the actual column is real.
A6: How the budget was constructed
B7: Anchor | E7: FY2023 actual, as filed. A board approving a FY2024 budget in late FY2023 would have had the FY2023 result in front of it and little else.
B8: Revenue | E8: Planned to grow 12% on FY2023. The organization had just come through two years of 60%-plus growth driven by humanitarian response funding, and a finance committee would reasonably assume that could not repeat. Twelve percent is deliberately cautious relative to recent experience.
B9: Expenses | E9: Planned to grow 26%, roughly double the revenue plan. This is the deliberate deployment of accumulated reserve into program capacity, which is exactly what a board sitting on two years of expenses in net assets would instruct management to do.
B10: Volume | E10: Participants planned to grow 18%, ahead of the expense plan, on the assumption that expansion comes partly through lower-cost digital channels.
B11: Mix | E11: Revenue and expense category splits held at their FY2023 proportions. A budget built a year ahead would not usually re-forecast mix in detail.
A13: Budget drivers
B14: Driver | C14: Value | D14: Tier | E14: Note
B15: Revenue growth on FY2023 | C15: 0.12 | D15: SYNTHETIC
B16: Expense growth on FY2023 | C16: 0.26 | D16: SYNTHETIC
B17: Participant growth on FY2023 | C17: 0.18 | D17: SYNTHETIC
A19: Independent analysis prepared from public information for portfolio and educational purposes. Not affiliated with, endorsed by, or reviewed by Upwardly Global. Historical totals are as filed; all forward-looking and program-level figures are analyst assumptions and are not the organization's plans or guidance.

Sheet Variance decomposition
A1: Variance decomposition
A2: Splitting each variance into the part caused by doing more or less, and the part caused by each unit costing more or less. Without this split a variance number cannot be acted on.
A4: Program cost variance bridge
A5: Component | B5: Amount | E5: How it is calculated
A6: Budgeted program cost | B6: ='Budget vs actual'!B12
A7: Budgeted participants | B7: ='Budget vs actual'!B27
A8: Budgeted cost per participant | B8: ='Budget vs actual'!B29
A9: Actual participants | B9: ='Budget vs actual'!C27
A10: Actual cost per participant | B10: ='Budget vs actual'!C29
A11: Actual program cost | B11: ='Budget vs actual'!C12
A13: Total program cost variance | B13: =B11-B6
A14: Volume variance | B14: =(B9-B7)*B8 | E14: Change in participants, valued at the BUDGETED cost per participant. This is the cost of doing more or less than planned.
A15: Rate variance | B15: =(B10-B8)*B9 | E15: Change in cost per participant, valued at ACTUAL participants. This is the cost of each unit being more or less expensive than planned.
A16: Check: volume plus rate equals total | B16: =IF(ABS(B14+B15-B13)<1,"ok","CHECK") | E16: The two effects must reconcile exactly. This ordering charges the interaction term to rate; the reverse convention is equally valid but must be stated, which is why it is stated here.
A18: Funding variance by source
A19: Category | B19: Budget | C19: Actual | D19: Variance | E19: Note
A20: Individual donations | B20: ='Budget vs actual'!B6*0.12 | C20: ='Budget vs actual'!C6*0.12 | D20: =C20-B20
A21: Corporate donations | B21: ='Budget vs actual'!B6*0.21 | C21: ='Budget vs actual'!C6*0.21 | D21: =C21-B21
A22: Foundation grants | B22: ='Budget vs actual'!B6*0.44 | C22: ='Budget vs actual'!C6*0.44 | D22: =C22-B22
A23: Government funding | B23: ='Budget vs actual'!B6*0.19 | C23: ='Budget vs actual'!C6*0.19 | D23: =C23-B23
A24: Fundraising events | B24: ='Budget vs actual'!B6*0.04 | C24: ='Budget vs actual'!C6*0.04 | D24: =C24-B24
A25: Total contributions variance | B25: =SUM(B20:B24) | C25: =SUM(C20:C24) | D25: =SUM(D20:D24)
A26: The category split is modelled at constant shares, so this table apportions the total contribution variance rather than explaining it. It is honest about what it can and cannot show: without the FY2024 Schedule B or a grants schedule, which funder moved is not publicly determinable.
A27: Personnel variance
A28: Budgeted personnel cost | B28: ='Budget vs actual'!B18
A29: Actual personnel cost | B29: ='Budget vs actual'!C18
A30: Total personnel variance | B30: =B29-B28
A31: Personnel as a share of expenses, budget | B31: =B28/'Budget vs actual'!B15
A32: Personnel as a share of expenses, actual | B32: =B29/'Budget vs actual'!C15 | E32: A personnel variance that is large in dollars but flat as a share of expenses is a scale story, not an efficiency story.
A34: Cost per participant bridge
A35: Budgeted cost per participant | B35: =B8
A36: Effect of fixed-cost absorption | B36: =-(B6/B7)*(1-B7/B9) | E36: Spreading the planned program cost over a different number of participants. Negative means more participants diluted the fixed base.
A37: Effect of total spend differing from plan | B37: =(B11-B6)/B9
A38: Actual cost per participant | B38: =B35+B36+B37
A39: Check: bridge ties to actual | B39: =IF(ABS(B38-B10)<0.01,"ok","CHECK")

Sheet Management commentary
A1: Management commentary on FY2024 variances
A2: Written against the reconstructed budget. Figures are quoted from the decomposition sheet.
B4: Headline
B5: Revenue of $28,580,411 finished $3,502,445 (14.0%) ahead of the $25,077,966 plan. Expenses of $18,275,646 finished $1,064,828 (6.2%) above the $17,210,818 plan. The operating surplus of $10,304,765 was therefore $2,437,617 (31.0%) better than budgeted. On the face of it this is a good year. The decomposition below argues that the most important variance in the file is a small unfavourable one, not the large favourable one.
B7: Quality of the revenue beat
B8: Of the $3,502,445 revenue overperformance, $740,194 - 21.1% of it - is investment and other income, which came in 107.5% above plan simply because the accumulated reserve is large and returns were strong. That is a balance sheet outcome, not a fundraising one, and it will reverse if markets do. Contributions beat plan by $2,813,101 (12.1%), which is the number that reflects actual fundraising performance. Program service revenue was the one revenue line to miss, coming in $50,850 (4.3%) below plan.
B10: Program cost variance, decomposed
B11: Program services spending exceeded budget by $870,312 (6.5%). Splitting that into its two causes: $658,965, or 75.7% of the overrun, is volume - the organization served 10,786 participants against a plan of 10,283, 503 more people than budgeted, valued at the budgeted unit cost. The remaining $211,347 is rate: cost per participant came in at $1,330 against $1,310 planned, 1.5% above. Program expense exceeded budget primarily because participant acquisition ran ahead of the planned expansion, with only a quarter of the overrun attributable to unit costs rising faster than assumed.
B13: The variance that actually matters
B14: Successful outcomes came in at 1,495 against a plan of 1,524 - 29 fewer, 1.9% below budget - in a year when the organization served 503 more participants than planned. The outcome rate fell to 13.9% from the 14.8% assumed in the budget. Had the planned conversion rate held on the actual participant base, the organization would have produced roughly 1,599 placements; the shortfall of about 104 is the cost of the mix shift. Growth came disproportionately through lower-converting channels. The organization bought reach and reported it as growth, and reach is not the mission.
B16: What that implies operationally
B17: A favourable volume variance sitting alongside an unfavourable outcome variance is a mix problem, not a cost problem, and cost discipline will not fix it. The relevant question for FY2025 is not whether the extra $658,965 of program spend was justified, but whether it was spent in the right channels. 06_Program_Economics.xlsx sets out the per-program cost per successful outcome, and 07_Resource_Allocation_Model.xlsx shows that the answer changes entirely depending on whether management is buying placement count or earnings gain. That choice should be made explicitly at budget time rather than emerging from where the marginal dollar happened to land.
B19: Support costs
B20: Management and general rose only 2.8% against plan while program services rose 6.5%, so support costs did not drive the overrun. The program expense ratio finished at 78.5%, well clear of the 65% BBB Standard 8 minimum; the administrative ratio at 12.0%; and fundraising cost 6.7 cents per dollar raised against a 35 cent BBB Standard 9 ceiling. On every conventional stewardship measure this organization is comfortable. None of those ratios speak to whether the money is being spent on the right programs, which is the harder question and the one the rest of this model is about.
... B23: Net assets closed FY2024 at $39,907,054, or 2.18 times annual expenses and 24 months of liquid runway. BBB Standard 10 flags unrestricted net assets above three times annual expenses. The board approved a 26% expense increase for FY2024 specifically to deploy reserve into programs; expenses grew 6.2% faster than that, which is the right direction, but revenue grew faster still and the surplus came in 31.0% ahead of plan. A fifth consecutive surplus of this size moves the organization toward the accumulation ceiling, not away from it. The FY2025 budget conversation should start there.
A25: Independent analysis prepared from public information for portfolio and educational purposes. Not affiliated with, endorsed by, or reviewed by Upwardly Global. Historical totals are as filed; all forward-looking and program-level figures are analyst assumptions and are not the organization's plans or guidance.
