Workbook

Sheet Source data
A1: Source data
A2: Upwardly Global, EIN 94-3346127. Public Form 990 figures and the modelled splits this workbook depends on. Restated here so the file stands alone.
A4: Line | B4: FY2019 | C4: FY2020 | D4: FY2021 | E4: FY2022 | F4: FY2023 | G4: FY2024 | H4: Tier | I4: Note
A5: Form 990 as filed
A6: Contributions and grants | B6: 6528091 | C6: 6738370 | D6: 11624463 | E6: 18348946 | F6: 20709887 | G6: 26008174 | H6: PUBLIC
A7: Program service revenue | B7: 353671 | C7: 304509 | D7: 383141 | E7: 1064285 | F7: 1066130 | G7: 1143216 | H7: PUBLIC
A8: Investment and other income | B8: 3602 | C8: 21624 | D8: 237 | E8: 14416 | F8: 672813 | G8: 1429021 | H8: PUBLIC
A9: Less: fundraising event costs and asset-sale losses | B9: -135303 | C9: -48199 | D9: -34318 | E9: -121695 | F9: -57789 | G9: 0 | H9: DERIVED
A10: Total revenue | B10: 6750061 | C10: 7016304 | D10: 11973523 | E10: 19305952 | F10: 22391041 | G10: 28580411 | H10: PUBLIC
A11: Total functional expenses | B11: 5531091 | C11: 5670504 | D11: 6893690 | E11: 9316393 | F11: 13659379 | G11: 18275646 | H11: PUBLIC
A12: Officer compensation | B12: 336307 | C12: 348404 | D12: 537859 | E12: 642262 | F12: 502983 | G12: 1026038 | H12: PUBLIC
A13: Other salaries and wages | B13: 3257098 | C13: 3406913 | D13: 3755210 | E13: 5321071 | F13: 7253251 | G13: 9234306 | H13: PUBLIC
A14: Payroll taxes | B14: 283482 | C14: 290730 | D14: 339149 | E14: 454590 | F14: 606465 | G14: 800307 | H14: PUBLIC
A15: Total assets | B15: 4915534 | C15: 7157462 | D15: 12593796 | E15: 23406064 | F15: 31782416 | G15: 42583791 | H15: PUBLIC
A16: Total liabilities | B16: 461151 | C16: 1357279 | D16: 1713780 | E16: 2536489 | F16: 2181179 | G16: 2676737 | H16: PUBLIC
A17: Net assets | B17: =B15-B16 | C17: =C15-C16 | D17: =D15-D16 | E17: =E15-E16 | F17: =F15-F16 | G17: =G15-G16 | H17: DERIVED
A19: Modelled functional expense split
A20: Program services share | B20: 0.762 | C20: 0.768 | D20: 0.774 | E20: 0.78 | F20: 0.783 | G20: 0.785 | H20: SYNTHETIC
A21: Management and general share | B21: 0.14 | C21: 0.137 | D21: 0.134 | E21: 0.129 | F21: 0.124 | G21: 0.12 | H21: SYNTHETIC
A22: Fundraising share | B22: 0.098 | C22: 0.095 | D22: 0.092 | E22: 0.091 | F22: 0.093 | G22: 0.095 | H22: SYNTHETIC
A24: Derived expense lines
A25: Program services | B25: =B11*B20 | C25: =C11*C20 | D25: =D11*D20 | E25: =E11*E20 | F25: =F11*F20 | G25: =G11*G20
A26: Management and general | B26: =B11*B21 | C26: =C11*C21 | D26: =D11*D21 | E26: =E11*E21 | F26: =F11*F21 | G26: =G11*G21
A27: Fundraising | B27: =B11*B22 | C27: =C11*C22 | D27: =D11*D22 | E27: =E11*E22 | F27: =F11*F22 | G27: =G11*G22
A29: Interpolation anchors (published observations)
A30: 2022 participants | B30: 7041 | H30: PUBLIC
A31: 2025 participants | B31: 13350 | H31: PUBLIC
A32: Participant growth per year | B32: =(B31/B30)^(1/3)-1 | H32: DERIVED
A33: 2022 placements | B33: 1116 | H33: PUBLIC
A34: 2025 placements | B34: 1730 | H34: PUBLIC
A35: Placement growth per year | B35: =(B34/B33)^(1/3)-1 | H35: DERIVED
A37: Program volume
A38: Participants served | B38: =$B$30*(1+$B$32)^(2019-2022) | C38: =$B$30*(1+$B$32)^(2020-2022) | D38: =$B$30*(1+$B$32)^(2021-2022) | E38: =$B$30*(1+$B$32)^(2022-2022) | F38: =$B$30*(1+$B$32)^(2023-2022) | G38: =$B$30*(1+$B$32)^(2024-2022) | H38: DERIVED
A39: Successful outcomes | B39: =$B$33*(1+$B$35)^(2019-2022) | C39: =$B$33*(1+$B$35)^(2020-2022) | D39: =$B$33*(1+$B$35)^(2021-2022) | E39: =$B$33*(1+$B$35)^(2022-2022) | F39: =$B$33*(1+$B$35)^(2023-2022) | G39: =$B$33*(1+$B$35)^(2024-2022) | H39: DERIVED
A41: Participant and placement counts are published for 2022 and 2025 only. Other years are interpolated at constant growth between those two observations, which fixes the series with no free parameters. The back-cast to FY2019 through FY2021 is the weakest link and should be read as illustrative.

Sheet Program inputs
A1: Program inputs
A2: The four-program portfolio. Participant and outcome counts reconcile to the FY2024 totals derived from published data; costs reconcile to the modelled program expense pool. The split across programs is an analyst assumption.
A4: Input | B4: Career Coaching | C4: Digital Learning | D4: Credential Support | E4: Partner Capacity | F4: Total | G4: Tier | H4: Note
A5: Volume
A6: Participants enrolled | B6: 2050 | C6: 7395 | D6: 700 | E6: 641 | F6: =SUM(B6:E6) | G6: SYNTHETIC | H6: Sums to the FY2024 total interpolated from the published 2022 and 2025 observations.
A7: Successful outcomes (placements) | B7: 861 | C7: 333 | D7: 217 | E7: 83 | F7: =SUM(B7:E7) | G7: SYNTHETIC | H7: Sums to the FY2024 placement total on the same basis.
A8: Completion rate | B8: 0.71 | C8: 0.24 | D8: 0.58 | E8: 0.46 | G8: SYNTHETIC | H8: Share of enrolled participants who finish the program. Distinct from the outcome rate.
A10: Cost
A11: Program cost | B11: 7890000 | C11: 2220000 | D11: 2940000 | E11: 1296382 | F11: =SUM(B11:E11) | G11: SYNTHETIC | H11: Sums to the modelled FY2024 program expense pool.
A12: Direct cost share | B12: 0.72 | C12: 0.58 | D12: 0.76 | E12: 0.64 | G12: SYNTHETIC | H12: Remainder is allocated indirect cost - supervision, platform, evaluation, shared space.
A14: Delivery and capacity
A15: Staff hours per participant | B15: 39 | C15: 2.5 | D15: 60 | E15: 15.584555 | G15: SYNTHETIC | H15: Set so total delivery hours tie to the staffing model: 121 FTE x 74% program share x 1,680 productive hours.
A16: Maximum servable participants | B16: 3400 | C16: 15000 | D16: 1150 | E16: 1500 | F16: =SUM(B16:E16) | G16: SYNTHETIC | H16: Demand and delivery ceiling. Binds the allocation model in 07.
A17: Minimum viable funding | B17: 4500000 | C17: 1200000 | D17: 1800000 | E17: 700000 | F17: =SUM(B17:E17) | G17: SYNTHETIC | H17: Below this the program cannot retain its delivery team.
A19: Outcome value
A20: Average salary gain per placement | B20: 61000 | C20: 37000 | D20: 88000 | E20: 46500 | G20: SYNTHETIC | H20: Increase in annual earnings against the participant's pre-program position.
A22: Reconciliation to public data
A23: Check | B23: Modelled | C23: Control total | D23: Difference | E23: Result
A24: Participants tie to the FY2024 derived total | B24: =B6+C6+D6+E6 | C24: ='Source data'!G38 | D24: =B24-C24 | E24: =IF(ABS(D24)<1,"PASS","FAIL")
A25: Outcomes tie to the FY2024 derived total | B25: =B7+C7+D7+E7 | C25: ='Source data'!G39 | D25: =B25-C25 | E25: =IF(ABS(D25)<1,"PASS","FAIL")
A26: Program costs tie to the modelled expense pool | B26: =B11+C11+D11+E11 | C26: ='Source data'!G25 | D26: =B26-C26 | E26: =IF(ABS(D26)<1,"PASS","FAIL")
A28: What each program is
A29: Career Coaching (CCP) | B29: Intensive one-to-one coaching for work-authorized immigrant and refugee professionals: resume and interview preparation, sector navigation, employer introductions. High touch, high cost per participant, high placement rate. The organization's flagship service line.
A30: Digital Learning (DLP) | B30: Self-serve online curriculum and community, open to any eligible jobseeker. Very low marginal cost per participant and correspondingly low conversion to placement, but it is the only channel that reaches jobseekers at national scale.
A31: Credential Support (CRS) | B31: Support for foreign-credentialed professionals - physicians, engineers, accountants - navigating US licensure and re-credentialing. Small, expensive, slow, and by far the largest earnings gain per successful outcome.
A32: Partner Capacity (PCB) | B32: Training and tooling delivered to staff at partner workforce development organizations, who then serve jobseekers directly. Outcomes are attributed at a discount because delivery is indirect. Its case rests on sector leverage rather than unit cost.
A34: Independent analysis prepared from public information for portfolio and educational purposes. Not affiliated with, endorsed by, or reviewed by Upwardly Global. Historical totals are as filed; all forward-looking and program-level figures are analyst assumptions and are not the organization's plans or guidance.

Sheet Program comparison
A1: Program comparison
A2: The same four programs ranked on each measure. They rank differently on each one, which is the point.
A4: Program | B4: Cost | C4: Participants | D4: Outcomes | E4: Cost per participant | F4: Cost per outcome | G4: Outcome rate | H4: Gain per $ | J4: Note
A5: Career Coaching | B5: ='Program economics'!B9 | C5: ='Program economics'!B6 | D5: ='Program economics'!B8 | E5: ='Program economics'!B13 | F5: ='Program economics'!B15 | G5: ='Program economics'!B19 | H5: ='Program economics'!B37
A6: Digital Learning | B6: ='Program economics'!C9 | C6: ='Program economics'!C6 | D6: ='Program economics'!C8 | E6: ='Program economics'!C13 | F6: ='Program economics'!C15 | G6: ='Program economics'!C19 | H6: ='Program economics'!C37
A7: Credential Support | B7: ='Program economics'!D9 | C7: ='Program economics'!D6 | D7: ='Program economics'!D8 | E7: ='Program economics'!D13 | F7: ='Program economics'!D15 | G7: ='Program economics'!D19 | H7: ='Program economics'!D37
A8: Partner Capacity | B8: ='Program economics'!E9 | C8: ='Program economics'!E6 | D8: ='Program economics'!E8 | E8: ='Program economics'!E13 | F8: ='Program economics'!E15 | G8: ='Program economics'!E19 | H8: ='Program economics'!E37
A9: Portfolio | B9: ='Program economics'!F9 | C9: ='Program economics'!F6 | D9: ='Program economics'!F8 | E9: ='Program economics'!F13 | F9: ='Program economics'!F15 | G9: ='Program economics'!F19 | H9: ='Program economics'!F37
A11: Rank on each measure (1 = best)
A12: Program | E12: Cost per participant | F12: Cost per outcome | G12: Outcome rate | H12: Gain per $ | J12: Combined rank
A13: Career Coaching | E13: =RANK(E5,$E$5:$E$8,1) | F13: =RANK(F5,$F$5:$F$8,1) | G13: =RANK(G5,$G$5:$G$8,0) | H13: =RANK(H5,$H$5:$H$8,0) | J13: =SUM(E13:H13)
A14: Digital Learning | E14: =RANK(E6,$E$5:$E$8,1) | F14: =RANK(F6,$F$5:$F$8,1) | G14: =RANK(G6,$G$5:$G$8,0) | H14: =RANK(H6,$H$5:$H$8,0) | J14: =SUM(E14:H14)
A15: Credential Support | E15: =RANK(E7,$E$5:$E$8,1) | F15: =RANK(F7,$F$5:$F$8,1) | G15: =RANK(G7,$G$5:$G$8,0) | H15: =RANK(H7,$H$5:$H$8,0) | J15: =SUM(E15:H15)
A16: Partner Capacity | E16: =RANK(E8,$E$5:$E$8,1) | F16: =RANK(F8,$F$5:$F$8,1) | G16: =RANK(G8,$G$5:$G$8,0) | H16: =RANK(H8,$H$5:$H$8,0) | J16: =SUM(E16:H16)
A18: A combined rank is shown because reviewers always ask for one, and it is the least useful number on the sheet. Adding ordinal ranks across measures with different units implies they matter equally, which no one has decided. The honest reading is the four columns to its left.
A54: What the comparison says
A55: Digital Learning produces a placement for $6,667 against $15,619 for Partner Capacity - a 2.3x difference. On cost per placement alone the allocation decision looks obvious.
A56: It is not obvious. Digital Learning converts only 4.5% of enrolled participants and its placements carry an average earnings gain of $37,000. Credential Support converts 31.0% at $88,000 of gain - 2.4 times as much income mobility per person placed.
A57: Measured on earnings gain generated per dollar spent, the ranking changes: Career Coaching leads at $6.66 of first-year gain per dollar. Cost per placement and value per placement point in different directions, and no amount of further analysis resolves that. It is a choice about what the organization is for.
A58: Capacity is the constraint that decides how much the choice is worth. Digital Learning is running at 49% of its ceiling and Credential Support at 61%. Headroom, not preference, sets the upper bound on how far funding can be tilted toward either. 06_Resource_Allocation.xlsx solves that problem explicitly.
A59: Partner Capacity is the weakest program on every financial measure - $15,619 per placement, the second-lowest conversion rate, and the lowest capacity utilisation at 43%. Its case rests on sector leverage and on outcomes delivered through partners that this model attributes at a discount. That case may well be sound, but it is a strategic argument and should be defended as one rather than hidden inside a blended portfolio average.

Sheet Calibration check
A1: Calibration against published impact data
A2: The program mix is synthetic. This is the one place it can be tested against something real.
A4: Measure | B4: Model | C4: Published | D4: Variance | E4: Note
A5: Average salary gain per placement | B5: ='Program economics'!F35 | C5: 58790 | D5: =IFERROR(B5/C5-1,"n/a") | E5: The organization published $58,790 for 2025. The synthetic program mix was tuned so the blended figure it implies lands within about 1% of that. This is a weak test - one number, from a different year, that the mix was fitted to - but it is a real constraint and it is better than none.
A6: Participants served, FY2024 | B6: ='Program economics'!F6 | C6: ='Source data'!G38 | D6: =IFERROR(B6/C6-1,"n/a") | E6: Ties by construction to the count interpolated between the published 2022 and 2025 observations.
A7: Successful outcomes, FY2024 | B7: ='Program economics'!F8 | C7: ='Source data'!G39 | D7: =IFERROR(B7/C7-1,"n/a") | E7: Ties to the interpolated placement total on the same basis.
A8: Blended outcome rate | B8: ='Program economics'!F19 | C8: ='Source data'!G39/'Source data'!G38 | D8: =IFERROR(B8/C8-1,"n/a") | E8: Implied by the two lines above. The 2022 published figures give 15.9% and the 2025 figures 13.0%, so a FY2024 rate between those is consistent with the published record.
A10: What this check cannot do: it cannot validate the split of participants, costs or outcomes across the four programs, because no public data exists at that level. Everything on 'Program comparison' should be read as an internally consistent illustration of how a portfolio like this behaves, not as a measurement of how this organization's programs actually perform.

Sheet Program economics
A1: Program unit economics, FY2024
A2: Every figure calculated from 'Program inputs'. Change an input there and this sheet moves.
A4: Measure | B4: Career Coaching | C4: Digital Learning | D4: Credential Support | E4: Partner Capacity | F4: Portfolio | H4: Note
A5: Scale
A6: Participants enrolled | B6: ='Program inputs'!B6 | C6: ='Program inputs'!C6 | D6: ='Program inputs'!D6 | E6: ='Program inputs'!E6 | F6: =SUM(B6:E6)
A7: Participants completing | B7: ='Program inputs'!B6*'Program inputs'!B8 | C7: ='Program inputs'!C6*'Program inputs'!C8 | D7: ='Program inputs'!D6*'Program inputs'!D8 | E7: ='Program inputs'!E6*'Program inputs'!E8 | F7: =SUM(B7:E7)
A8: Successful outcomes | B8: ='Program inputs'!B7 | C8: ='Program inputs'!C7 | D8: ='Program inputs'!D7 | E8: ='Program inputs'!E7 | F8: =SUM(B8:E8)
A9: Program cost | B9: ='Program inputs'!B11 | C9: ='Program inputs'!C11 | D9: ='Program inputs'!D11 | E9: ='Program inputs'!E11 | F9: =SUM(B9:E9)
A10: Share of program spend | B10: =B9/$F$9 | C10: =C9/$F$9 | D10: =D9/$F$9 | E10: =E9/$F$9 | F10: =SUM(B10:E10)
A12: Unit cost
A13: Cost per participant | B13: =B9/B6 | C13: =C9/C6 | D13: =D9/D6 | E13: =E9/E6 | F13: =F9/F6 | H13: Program cost divided by enrolled participants.
A14: Cost per completer | B14: =B9/B7 | C14: =C9/C7 | D14: =D9/D7 | E14: =E9/E7 | F14: =F9/F7
A15: Cost per successful outcome | B15: =B9/B8 | C15: =C9/C8 | D15: =D9/D8 | E15: =E9/E8 | F15: =F9/F8 | H15: The single most decision-relevant cost measure in this workbook.
A17: Conversion
A18: Completion rate | B18: ='Program inputs'!B8 | C18: ='Program inputs'!C8 | D18: ='Program inputs'!D8 | E18: ='Program inputs'!E8 | F18: =F7/F6
A19: Outcome rate (of enrolled) | B19: =B8/B6 | C19: =C8/C6 | D19: =D8/D6 | E19: =E8/E6 | F19: =F8/F6
A20: Outcome rate (of completers) | B20: =B8/B7 | C20: =C8/C7 | D20: =D8/D7 | E20: =E8/E7 | F20: =F8/F7 | H20: Separating these two matters. A low outcome rate caused by drop-out is a retention problem; one caused by completers not being placed is a placement problem. They have different fixes.
A22: Cost structure
A23: Direct cost | B23: =B9*'Program inputs'!B12 | C23: =C9*'Program inputs'!C12 | D23: =D9*'Program inputs'!D12 | E23: =E9*'Program inputs'!E12 | F23: =SUM(B23:E23)
A24: Indirect cost | B24: =B9-B23 | C24: =C9-C23 | D24: =D9-D23 | E24: =E9-E23 | F24: =SUM(B24:E24)
A25: Indirect as a share of program cost | B25: =B24/B9 | C25: =C24/C9 | D25: =D24/D9 | E25: =E24/E9 | F25: =F24/F9
A27: Delivery capacity
A28: Staff hours consumed | B28: ='Program inputs'!B6*'Program inputs'!B15 | C28: ='Program inputs'!C6*'Program inputs'!C15 | D28: ='Program inputs'!D6*'Program inputs'!D15 | E28: ='Program inputs'!E6*'Program inputs'!E15 | F28: =SUM(B28:E28)
A29: Implied programme FTE | B29: =B28/1680 | C29: =C28/1680 | D29: =D28/1680 | E29: =E28/1680 | F29: =SUM(B29:E29)
A30: Staff hours per successful outcome | B30: =B28/B8 | C30: =C28/C8 | D30: =D28/D8 | E30: =E28/E8 | F30: =F28/F8 | H30: The capacity equivalent of cost per outcome. Money is not the only scarce input.
A31: Capacity utilisation | B31: =B6/'Program inputs'!B16 | C31: =C6/'Program inputs'!C16 | D31: =D6/'Program inputs'!D16 | E31: =E6/'Program inputs'!E16 | F31: =F6/SUM('Program inputs'!B16:'Program inputs'!E16) | H31: How full each programme is against its ceiling. Headroom here is what the allocation model can actually buy.
A32: Funding utilisation against minimum viable | B32: =B9/'Program inputs'!B17 | C32: =C9/'Program inputs'!C17 | D32: =D9/'Program inputs'!D17 | E32: =E9/'Program inputs'!E17 | F32: =F9/SUM('Program inputs'!B17:'Program inputs'!E17) | H32: How far above its funding floor each programme sits. A ratio near 1.0 means the programme has no room to absorb a cut without losing its team.
A34: Outcome value
A35: Average salary gain per placement | B35: ='Program inputs'!B20 | C35: ='Program inputs'!C20 | D35: ='Program inputs'!D20 | E35: ='Program inputs'!E20 | F35: =F36/F8
A36: Total first-year earnings gain | B36: =B8*B35 | C36: =C8*C35 | D36: =D8*D35 | E36: =E8*E35 | F36: =SUM(B36:E36)
A37: Earnings gain per dollar of programme cost | B37: =B36/B9 | C37: =C36/C9 | D37: =D36/D9 | E37: =E36/E9 | F37: =F36/F9 | H37: First-year gross earnings gain per dollar spent. Not a social return figure - no attribution, deadweight, drop-off or discounting has been applied yet.

Sheet Social return (caveated)
A1: Social return on investment - low confidence, reported as a range
A2: This is the least reliable analysis in the project and is placed last deliberately.
A4: Read this before quoting any number below. Every parameter driving these ratios - attribution, deadweight, drop-off, persistence, benefit horizon - is an assumption with no empirical support in this project. The headline ratio moves by more than a factor of five across plausible values. Cost per successful outcome, on 'Program economics', rests on far fewer assumptions and is the measure management should steer on.
A6: Parameters
A7: Parameter | B7: Value | H7: What it does
A8: Benefit horizon years | B8: 3 | H8: Number of years the earnings gain is counted for. Doubling it roughly doubles the ratio.
A9: Discount rate | B9: 0.03 | H9: Applied to future years of benefit.
A10: Attribution rate | B10: 0.55 | H10: Share of the earnings gain credited to the program rather than to the participant's own effort, credentials and labour market conditions. The single most consequential assumption here.
A11: Deadweight rate | B11: 0.25 | H11: Share of the gain that would have occurred anyway without the program.
A12: Dropoff rate | B12: 0.2 | H12: Annual decay in the attributable benefit as the program's influence fades.
A13: Persistence rate | B13: 0.78 | H13: Share of placements still employed at twelve months.
A15: Result at the stated parameters
A16: Measure | B16: Career Coaching | C16: Digital Learning | D16: Credential Support | E16: Partner Capacity | F16: Portfolio
A17: Gross first-year earnings gain | B17: 52521000 | C17: 12321000 | D17: 19096000 | E17: 3859500
A18: Present value over the horizon | B18: 1.0905298e+08 | C18: 25582944 | D18: 39650345 | E18: 8013746.6
A19: Attributable value after deadweight | B19: 44984355 | C19: 10552964 | D19: 16355767 | E19: 3305670.5 | F19: 75198757
A20: Program cost | B20: 7890000.1 | C20: 2220000 | D20: 2940000 | E20: 1296382 | F20: 14346382
A21: Social return ratio | B21: 5.7014392 | C21: 4.7535875 | D21: 5.5631861 | E21: 2.5499201 | F21: 5.241653
A24: How unstable that number is
A25: Attribution rate | B25: 1-year horizon | C25: 3-year horizon | D25: 5-year horizon
A26: 35% | B26: 1.6064568 | C26: 3.3355974 | D26: 4.3787211
A27: 45% | B27: 2.0654445 | C27: 4.2886252 | D27: 5.6297843
A28: 55% | B28: 2.5244322 | C28: 5.241653 | D28: 6.8808474
A29: 65% | B29: 2.9834199 | C29: 6.1946809 | D29: 8.1319106
A30: 75% | B30: 3.4424075 | C30: 7.1477087 | D30: 9.3829738
A32: The portfolio ratio ranges from 1.61 to 9.38 across this grid alone - a spread of 5.8 times - and the grid varies only two of the six parameters. A social return figure quoted without its assumptions is not a finding; it is a decoration. That is why the management report leads on cost per successful outcome instead.
A34: What is deliberately excluded
A35: - Fiscal effects. Higher earnings generate additional tax revenue and reduce transfer payments. Both are real and both are commonly used to inflate social return figures. Neither is included here.
A36: - Second-order and household effects. Effects on participants' children, on household stability, on health outcomes. Plausibly large, entirely unmeasured in this project.
A37: - Employer-side value. The value to employers of filling skilled roles they could not otherwise fill. Real, and not estimable from public data.
A38: - Earnings gains beyond the stated horizon. Placements plainly produce value past year three or five; the horizon is a modelling convenience, not a claim that the benefit stops.
A39: - Any counterfactual evidence at all. There is no comparison group here. Attribution and deadweight are assumptions standing in for a study that has not been done, and no amount of arithmetic can substitute for one.
